odoo/addons/cross_connect_server/README.rst
odoo/addons/cross_connect_server/__init__.py
odoo/addons/cross_connect_server/__manifest__.py
odoo/addons/cross_connect_server/dependencies.py
odoo/addons/cross_connect_server/schemas.py
odoo/addons/cross_connect_server/i18n/cross_connect_server.pot
odoo/addons/cross_connect_server/i18n/it.po
odoo/addons/cross_connect_server/models/__init__.py
odoo/addons/cross_connect_server/models/cross_connect_client.py
odoo/addons/cross_connect_server/models/fastapi_endpoint.py
odoo/addons/cross_connect_server/models/res_users.py
odoo/addons/cross_connect_server/readme/CONTRIBUTORS.md
odoo/addons/cross_connect_server/readme/DESCRIPTION.md
odoo/addons/cross_connect_server/readme/USAGE.md
odoo/addons/cross_connect_server/routers/__init__.py
odoo/addons/cross_connect_server/routers/cross_connect.py
odoo/addons/cross_connect_server/security/ir_model_access.xml
odoo/addons/cross_connect_server/security/res_groups.xml
odoo/addons/cross_connect_server/static/description/icon.png
odoo/addons/cross_connect_server/static/description/index.html
odoo/addons/cross_connect_server/tests/__init__.py
odoo/addons/cross_connect_server/tests/test_cross_connect_server.py
odoo/addons/cross_connect_server/views/fastapi_endpoint_views.xml
odoo_addon_cross_connect_server-16.0.1.0.1.dist-info/METADATA
odoo_addon_cross_connect_server-16.0.1.0.1.dist-info/WHEEL
odoo_addon_cross_connect_server-16.0.1.0.1.dist-info/top_level.txt
odoo_addon_cross_connect_server-16.0.1.0.1.dist-info/RECORD
